Workbook

Sheet COVER
C4: Apple Inc. (NASDAQ: AAPL)
C6: https://www.sec.gov/Archives/edgar/data/320193/000032019325000079/aapl-20250927.htm
C7: 3-Statement Financial Model
C10: Prepared by: Facundo Santiago Lezcano
C12: Date: September 2026
C14: Projection Period: 2026-2030
C16: Source: Apple Inc. FY2025 Form 10-K (fiscal year ended September 27, 2025)
C18: USD in millions unless otherwise stated
C23: README
C25: Source:
C26: Apple Inc. FY2025 Form 10-K filing, SEC EDGAR (filed October 31, 2025)
C28: Projection Period:
... C50: Intangibles are simplified in the PEP template - this keeps the Balance Sheet Check at 0.

Sheet ASSUMPTIONS
B1: Historical Results | D1: Forecast Period
B2: 2024A | C2: 2025A | D2: 2026F | E2: 2027F | F2: 2028F | G2: 2029F | H2: 2030F
A4: Assumptions
A6: Revenue Assumptions
A7: iPhone Growth (% Change) | C7: ='INCOME STATEMENT'!C7/'INCOME STATEMENT'!B7-1 -> 0.041767943 | D7: 0.03 | E7: 0.03 | F7: 0.035 | G7: 0.035 | H7: 0.035
A8: Mac Growth (% Change) | C8: ='INCOME STATEMENT'!C8/'INCOME STATEMENT'!B8-1 -> 0.12419957 | D8: 0.04 | E8: 0.04 | F8: 0.04 | G8: 0.04 | H8: 0.04
A9: iPad Growth (% Change) | C9: ='INCOME STATEMENT'!C9/'INCOME STATEMENT'!B9-1 -> 0.049786469 | D9: 0.03 | E9: 0.03 | F9: 0.03 | G9: 0.03 | H9: 0.03
A10: Wearables, Home and Accessories Growth (% Change) | C10: ='INCOME STATEMENT'!C10/'INCOME STATEMENT'!B10-1 -> -0.035643832 | D10: 0.02 | E10: 0.025 | F10: 0.025 | G10: 0.03 | H10: 0.03
A11: Services Growth (% Change) | C11: ='INCOME STATEMENT'!C12/'INCOME STATEMENT'!B12-1 -> 0.13506431 | D11: 0.12 | E11: 0.11 | F11: 0.1 | G11: 0.09 | H11: 0.09
A13: Margin Assumptions
A14: Products COGS (% of Products Revenue) | B14: ='INCOME STATEMENT'!B16/'INCOME STATEMENT'!B11 -> 0.62819382 | C14: ='INCOME STATEMENT'!C16/'INCOME STATEMENT'!C11 -> 0.6322935 | D14: 0.63 | E14: 0.63 | F14: 0.625 | G14: 0.625 | H14: 0.62
A15: Services COGS (% of Services Revenue) | B15: ='INCOME STATEMENT'!B17/'INCOME STATEMENT'!B12 -> 0.26119644 | C15: ='INCOME STATEMENT'!C17/'INCOME STATEMENT'!C12 -> 0.24591876 | D15: 0.24 | E15: 0.235 | F15: 0.23 | G15: 0.23 | H15: 0.225
A16: Research & Development (% of Total Revenue) | B16: ='INCOME STATEMENT'!B22/'INCOME STATEMENT'!B13 -> 0.080222998 | C16: ='INCOME STATEMENT'!C22/'INCOME STATEMENT'!C13 -> 0.083020754 | D16: 0.083 | E16: 0.083 | F16: 0.082 | G16: 0.082 | H16: 0.081
A17: Selling, General & Administrative (% of Total Revenue) | B17: ='INCOME STATEMENT'!B23/'INCOME STATEMENT'!B13 -> 0.066738272 | C17: ='INCOME STATEMENT'!C23/'INCOME STATEMENT'!C13 -> 0.066322889 | D17: 0.066 | E17: 0.066 | F17: 0.065 | G17: 0.065 | H17: 0.065
A18: Depreciation & Amortization (% of PP&E, Opening) | D18: 0.23 | E18: 0.23 | F18: 0.225 | G18: 0.225 | H18: 0.22
A19: Other Income/(Expense), net (% of Total Revenue) | B19: ='INCOME STATEMENT'!B28/'INCOME STATEMENT'!B13 -> 0.00068791796 | C19: ='INCOME STATEMENT'!C28/'INCOME STATEMENT'!C13 -> -0.00077133609 | D19: -0.001 | E19: -0.001 | F19: 0 | G19: 0 | H19: 0
A20: Tax Rate (% of Earnings Before Tax) | B20: ='INCOME STATEMENT'!B31/'INCOME STATEMENT'!B29 -> 0.24091185 | C20: ='INCOME STATEMENT'!C31/'INCOME STATEMENT'!C29 -> 0.15610002 | D20: 0.16 | E20: 0.16 | F20: 0.165 | G20: 0.165 | H20: 0.165
A22: Working Capital Assumptions
A23: DSO - Accounts Receivable (days) | B23: ='BALANCE SHEET'!B9/'INCOME STATEMENT'!B13*365 -> 31.185572 | C23: ='BALANCE SHEET'!C9/'INCOME STATEMENT'!C13*365 -> 34.886991 | D23: 33 | E23: 33 | F23: 33 | G23: 33 | H23: 33
A24: Vendor Non-Trade Receivables (days) | B24: ='BALANCE SHEET'!B10/'INCOME STATEMENT'!B13*365 -> 30.646988 | C24: ='BALANCE SHEET'!C10/'INCOME STATEMENT'!C13*365 -> 29.100997 | D24: 30 | E24: 30 | F24: 30 | G24: 30 | H24: 30
A25: DIO - Inventory (days, of Total Cost of Sales) | B25: ='BALANCE SHEET'!B11/'INCOME STATEMENT'!B18*365 -> 12.642571 | C25: ='BALANCE SHEET'!C11/'INCOME STATEMENT'!C18*365 -> 9.4454652 | D25: 10 | E25: 10 | F25: 10 | G25: 10 | H25: 10
A26: DPO - Accounts Payable (days, of Total Cost of Sales) | B26: ='BALANCE SHEET'!B22/'INCOME STATEMENT'!B18*365 -> 119.65848 | C26: ='BALANCE SHEET'!C22/'INCOME STATEMENT'!C18*365 -> 115.40052 | D26: 117 | E26: 117 | F26: 117 | G26: 117 | H26: 117
A27: Deferred Revenue (days, of Services Revenue) | B27: ='BALANCE SHEET'!B23/'INCOME STATEMENT'!B12*365 -> 31.30827 | C27: ='BALANCE SHEET'!C23/'INCOME STATEMENT'!C12*365 -> 30.2779 | D27: 30 | E27: 30 | F27: 30 | G27: 30 | H27: 30
A29: CapEx, Debt & Capital Return Assumptions
A30: Capital Expenditures ($mm) | B30: ='CASH FLOW STATEMENT'!B15 -> -9447 | C30: ='CASH FLOW STATEMENT'!C15 -> -12715 | D30: -13500 | E30: -14500 | F30: -15500 | G30: -16500 | H30: -17500
A31: Debt Issuance ($mm) | B31: 0 | C31: 4481 | D31: 0 | E31: 0 | F31: 0 | G31: 0 | H31: 0
A32: Debt Repayment ($mm) - Term Debt + Commercial Paper, net | B32: -5998 | C32: -12964 | D32: -9000 | E32: -8000 | F32: -7000 | G32: -6000 | H32: -5000
A33: Dividends Paid ($mm) | B33: -15234 | C33: -15421 | D33: -16200 | E33: -17000 | F33: -17850 | G33: -18750 | H33: -19700
A34: Share Repurchases ($mm) | B34: -94949 | C34: -90711 | D34: -95000 | E34: -95000 | F34: -95000 | G34: -95000 | H34: -95000
A35: Days in Period | B35: 365 | C35: 365 | D35: 365 | E35: 365 | F35: 365 | G35: 365 | H35: 365
A37: Share-based Compensation (% of Total Revenue) | B37: ='CASH FLOW STATEMENT'!B9/'INCOME STATEMENT'!B13 -> 0.029889908 | C37: ='CASH FLOW STATEMENT'!C9/'INCOME STATEMENT'!C13 -> 0.030908711 | D37: 0.03 | E37: 0.03 | F37: 0.03 | G37: 0.03 | H37: 0.03

Sheet INCOME STATEMENT
B1: Historical Results | D1: Forecast Period
B2: 2024A | C2: 2025A | D2: 2026F | E2: 2027F | F2: 2028F | G2: 2029F | H2: 2030F
A4: Income Statement
A6: Revenue
A7: iPhone | B7: 201183 | C7: 209586 | D7: =C7*(1+ASSUMPTIONS!D7) -> 215873.58 | E7: =D7*(1+ASSUMPTIONS!E7) -> 222349.79 | F7: =E7*(1+ASSUMPTIONS!F7) -> 230132.03 | G7: =F7*(1+ASSUMPTIONS!G7) -> 238186.65 | H7: =G7*(1+ASSUMPTIONS!H7) -> 246523.18
A8: Mac | B8: 29984 | C8: 33708 | D8: =C8*(1+ASSUMPTIONS!D8) -> 35056.32 | E8: =D8*(1+ASSUMPTIONS!E8) -> 36458.573 | F8: =E8*(1+ASSUMPTIONS!F8) -> 37916.916 | G8: =F8*(1+ASSUMPTIONS!G8) -> 39433.592 | H8: =G8*(1+ASSUMPTIONS!H8) -> 41010.936
A9: iPad | B9: 26694 | C9: 28023 | D9: =C9*(1+ASSUMPTIONS!D9) -> 28863.69 | E9: =D9*(1+ASSUMPTIONS!E9) -> 29729.601 | F9: =E9*(1+ASSUMPTIONS!F9) -> 30621.489 | G9: =F9*(1+ASSUMPTIONS!G9) -> 31540.133 | H9: =G9*(1+ASSUMPTIONS!H9) -> 32486.337
A10: Wearables, Home and Accessories | B10: 37005 | C10: 35686 | D10: =C10*(1+ASSUMPTIONS!D10) -> 36399.72 | E10: =D10*(1+ASSUMPTIONS!E10) -> 37309.713 | F10: =E10*(1+ASSUMPTIONS!F10) -> 38242.456 | G10: =F10*(1+ASSUMPTIONS!G10) -> 39389.729 | H10: =G10*(1+ASSUMPTIONS!H10) -> 40571.421
A11: Total Products Net Sales | B11: =SUM(B7:B10) -> 294866 | C11: =SUM(C7:C10) -> 307003 | D11: =SUM(D7:D10) -> 316193.31 | E11: =SUM(E7:E10) -> 325847.67 | F11: =SUM(F7:F10) -> 336912.89 | G11: =SUM(G7:G10) -> 348550.11 | H11: =SUM(H7:H10) -> 360591.88
A12: Services | B12: 96169 | C12: 109158 | D12: =C12*(1+ASSUMPTIONS!D11) -> 122256.96 | E12: =D12*(1+ASSUMPTIONS!E11) -> 135705.23 | F12: =E12*(1+ASSUMPTIONS!F11) -> 149275.75 | G12: =F12*(1+ASSUMPTIONS!G11) -> 162710.57 | H12: =G12*(1+ASSUMPTIONS!H11) -> 177354.52
A13: Total Net Sales | B13: =B11+B12 -> 391035 | C13: =C11+C12 -> 416161 | D13: =D11+D12 -> 438450.27 | E13: =E11+E12 -> 461552.9 | F13: =F11+F12 -> 486188.64 | G13: =G11+G12 -> 511260.67 | H13: =H11+H12 -> 537946.39
A15: Cost of Sales
A16: Products Cost of Sales | B16: 185233 | C16: 194116 | D16: =D11*ASSUMPTIONS!D14 -> 199201.79 | E16: =E11*ASSUMPTIONS!E14 -> 205284.03 | F16: =F11*ASSUMPTIONS!F14 -> 210570.56 | G16: =G11*ASSUMPTIONS!G14 -> 217843.82 | H16: =H11*ASSUMPTIONS!H14 -> 223566.96
A17: Services Cost of Sales | B17: 25119 | C17: 26844 | D17: =D12*ASSUMPTIONS!D15 -> 29341.67 | E17: =E12*ASSUMPTIONS!E15 -> 31890.728 | F17: =F12*ASSUMPTIONS!F15 -> 34333.422 | G17: =G12*ASSUMPTIONS!G15 -> 37423.43 | H17: =H12*ASSUMPTIONS!H15 -> 39904.766
A18: Total Cost of Sales | B18: =SUM(B16:B17) -> 210352 | C18: =SUM(C16:C17) -> 220960 | D18: =SUM(D16:D17) -> 228543.46 | E18: =SUM(E16:E17) -> 237174.76 | F18: =SUM(F16:F17) -> 244903.98 | G18: =SUM(G16:G17) -> 255267.25 | H18: =SUM(H16:H17) -> 263471.73
A19: Gross Margin | B19: =B13-B18 -> 180683 | C19: =C13-C18 -> 195201 | D19: =D13-D18 -> 209906.81 | E19: =E13-E18 -> 224378.14 | F19: =F13-F18 -> 241284.66 | G19: =G13-G18 -> 255993.43 | H19: =H13-H18 -> 274474.66
A21: Operating Expenses
A22: Research & Development | B22: 31370 | C22: 34550 | D22: =D13*ASSUMPTIONS!D16 -> 36391.372 | E22: =E13*ASSUMPTIONS!E16 -> 38308.891 | F22: =F13*ASSUMPTIONS!F16 -> 39867.468 | G22: =G13*ASSUMPTIONS!G16 -> 41923.375 | H22: =H13*ASSUMPTIONS!H16 -> 43573.658
A23: Selling, General & Administrative | B23: 26097 | C23: 27601 | D23: =D13*ASSUMPTIONS!D17 -> 28937.718 | E23: =E13*ASSUMPTIONS!E17 -> 30462.491 | F23: =F13*ASSUMPTIONS!F17 -> 31602.261 | G23: =G13*ASSUMPTIONS!G17 -> 33231.944 | H23: =H13*ASSUMPTIONS!H17 -> 34966.516
A24: Total Operating Expenses | B24: =SUM(B22:B23) -> 57467 | C24: =SUM(C22:C23) -> 62151 | D24: =SUM(D22:D23) -> 65329.09 | E24: =SUM(E22:E23) -> 68771.382 | F24: =SUM(F22:F23) -> 71469.73 | G24: =SUM(G22:G23) -> 75155.319 | H24: =SUM(H22:H23) -> 78540.174
A25: Operating Income | B25: =B19-B24 -> 123216 | C25: =C19-C24 -> 133050 | D25: =D19-D24 -> 144577.72 | E25: =E19-E24 -> 155606.75 | F25: =F19-F24 -> 169814.93 | G25: =G19-G24 -> 180838.11 | H25: =H19-H24 -> 195934.49
A28: Other Income/(Expense), net | B28: 269 | C28: -321 | D28: =D13*ASSUMPTIONS!D19 -> -438.45027 | E28: =E13*ASSUMPTIONS!E19 -> -461.5529 | F28: =F13*ASSUMPTIONS!F19 -> 0 | G28: =G13*ASSUMPTIONS!G19 -> 0 | H28: =H13*ASSUMPTIONS!H19 -> 0
A29: Income Before Provision for Income Taxes | B29: =B25+B28 -> 123485 | C29: =C25+C28 -> 132729 | D29: =D25+D28 -> 144139.27 | E29: =E25+E28 -> 155145.2 | F29: =F25+F28 -> 169814.93 | G29: =G25+G28 -> 180838.11 | H29: =H25+H28 -> 195934.49
A31: Provision for Income Taxes | B31: 29749 | C31: 20719 | D31: =D29*ASSUMPTIONS!D20 -> 23062.284 | E31: =E29*ASSUMPTIONS!E20 -> 24823.232 | F31: =F29*ASSUMPTIONS!F20 -> 28019.463 | G31: =G29*ASSUMPTIONS!G20 -> 29838.288 | H31: =H29*ASSUMPTIONS!H20 -> 32329.191
A32: Net Income | B32: =B29-B31 -> 93736 | C32: =C29-C31 -> 112010 | D32: =D29-D31 -> 121076.99 | E32: =E29-E31 -> 130321.97 | F32: =F29-F31 -> 141795.47 | G32: =G29-G31 -> 150999.82 | H32: =H29-H31 -> 163605.3

Sheet BALANCE SHEET
B1: Historical Results | D1: Forecast Period
B2: 2024A | C2: 2025A | D2: 2026F | E2: 2027F | F2: 2028F | G2: 2029F | H2: 2030F
A4: Balance Sheet
A6: Assets
A7: Cash & Cash Equivalents | B7: 29943 | C7: 35934 | D7: ='CASH FLOW STATEMENT'!D26 -> 49054.788 | E7: ='CASH FLOW STATEMENT'!E26 -> 70301.979 | F7: ='CASH FLOW STATEMENT'!F26 -> 102711.47 | G7: ='CASH FLOW STATEMENT'!G26 -> 145594.59 | H7: ='CASH FLOW STATEMENT'!H26 -> 200607.54
A8: Marketable Securities (Current) | B8: 35228 | C8: 18763 | D8: =C8 -> 18763 | E8: =D8 -> 18763 | F8: =E8 -> 18763 | G8: =F8 -> 18763 | H8: =G8 -> 18763
A9: Accounts Receivable | B9: 33410 | C9: 39777 | D9: ='INCOME STATEMENT'!D13*ASSUMPTIONS!D23/ASSUMPTIONS!D35 -> 39640.709 | E9: ='INCOME STATEMENT'!E13*ASSUMPTIONS!E23/ASSUMPTIONS!E35 -> 41729.44 | F9: ='INCOME STATEMENT'!F13*ASSUMPTIONS!F23/ASSUMPTIONS!F35 -> 43956.781 | G9: ='INCOME STATEMENT'!G13*ASSUMPTIONS!G23/ASSUMPTIONS!G35 -> 46223.568 | H9: ='INCOME STATEMENT'!H13*ASSUMPTIONS!H23/ASSUMPTIONS!H35 -> 48636.249
A10: Vendor Non-Trade Receivables | B10: 32833 | C10: 33180 | D10: ='INCOME STATEMENT'!D13*ASSUMPTIONS!D24/ASSUMPTIONS!D35 -> 36037.008 | E10: ='INCOME STATEMENT'!E13*ASSUMPTIONS!E24/ASSUMPTIONS!E35 -> 37935.855 | F10: ='INCOME STATEMENT'!F13*ASSUMPTIONS!F24/ASSUMPTIONS!F35 -> 39960.71 | G10: ='INCOME STATEMENT'!G13*ASSUMPTIONS!G24/ASSUMPTIONS!G35 -> 42021.425 | H10: ='INCOME STATEMENT'!H13*ASSUMPTIONS!H24/ASSUMPTIONS!H35 -> 44214.772
A11: Inventories | B11: 7286 | C11: 5718 | D11: ='INCOME STATEMENT'!D18*ASSUMPTIONS!D25/ASSUMPTIONS!D35 -> 6261.4645 | E11: ='INCOME STATEMENT'!E18*ASSUMPTIONS!E25/ASSUMPTIONS!E35 -> 6497.9387 | F11: ='INCOME STATEMENT'!F18*ASSUMPTIONS!F25/ASSUMPTIONS!F35 -> 6709.698 | G11: ='INCOME STATEMENT'!G18*ASSUMPTIONS!G25/ASSUMPTIONS!G35 -> 6993.6232 | H11: ='INCOME STATEMENT'!H18*ASSUMPTIONS!H25/ASSUMPTIONS!H35 -> 7218.4036
A12: Other Current Assets | B12: 14287 | C12: 14585 | D12: =C12 -> 14585 | E12: =D12 -> 14585 | F12: =E12 -> 14585 | G12: =F12 -> 14585 | H12: =G12 -> 14585
A13: Total Current Assets | B13: =SUM(B7:B12) -> 152987 | C13: =SUM(C7:C12) -> 147957 | D13: =SUM(D7:D12) -> 164341.97 | E13: =SUM(E7:E12) -> 189813.21 | F13: =SUM(F7:F12) -> 226686.66 | G13: =SUM(G7:G12) -> 274181.21 | H13: =SUM(H7:H12) -> 334024.97
A15: Marketable Securities (Non-current) | B15: 91479 | C15: 77723 | D15: =C15 -> 77723 | E15: =D15 -> 77723 | F15: =E15 -> 77723 | G15: =F15 -> 77723 | H15: =G15 -> 77723
A16: Property, Plant & Equipment, net | B16: 45680 | C16: 49834 | D16: ='SUPPORTING SCHEDULES'!D19 -> 51872.18 | E16: ='SUPPORTING SCHEDULES'!E19 -> 54441.579 | F16: ='SUPPORTING SCHEDULES'!F19 -> 57692.223 | G16: ='SUPPORTING SCHEDULES'!G19 -> 61211.473 | H16: ='SUPPORTING SCHEDULES'!H19 -> 65244.949
A17: Other Non-current Assets (Plug) | B17: =B34-SUM(B7:B12)-B15-B16 -> 74834 | C17: =C34-SUM(C7:C12)-C15-C16 -> 83727 | D17: =D34-SUM(D7:D12)-D15-D16 -> 83727 | E17: =E34-SUM(E7:E12)-E15-E16 -> 83727 | F17: =F34-SUM(F7:F12)-F15-F16 -> 83727 | G17: =G34-SUM(G7:G12)-G15-G16 -> 83727 | H17: =H34-SUM(H7:H12)-H15-H16 -> 83727
A18: Total Non-current Assets | B18: =SUM(B15:B17) -> 211993 | C18: =SUM(C15:C17) -> 211284 | D18: =SUM(D15:D17) -> 213322.18 | E18: =SUM(E15:E17) -> 215891.58 | F18: =SUM(F15:F17) -> 219142.22 | G18: =SUM(G15:G17) -> 222661.47 | H18: =SUM(H15:H17) -> 226694.95
A19: Total Assets | B19: =B13+B18 -> 364980 | C19: =C13+C18 -> 359241 | D19: =D13+D18 -> 377664.15 | E19: =E13+E18 -> 405704.79 | F19: =F13+F18 -> 445828.89 | G19: =G13+G18 -> 496842.68 | H19: =H13+H18 -> 560719.92
A21: Liabilities
A22: Accounts Payable | B22: 68960 | C22: 69860 | D22: ='INCOME STATEMENT'!D18*ASSUMPTIONS!D26/ASSUMPTIONS!D35 -> 73259.135 | E22: ='INCOME STATEMENT'!E18*ASSUMPTIONS!E26/ASSUMPTIONS!E35 -> 76025.883 | F22: ='INCOME STATEMENT'!F18*ASSUMPTIONS!F26/ASSUMPTIONS!F35 -> 78503.467 | G22: ='INCOME STATEMENT'!G18*ASSUMPTIONS!G26/ASSUMPTIONS!G35 -> 81825.391 | H22: ='INCOME STATEMENT'!H18*ASSUMPTIONS!H26/ASSUMPTIONS!H35 -> 84455.322
A23: Deferred Revenue | B23: 8249 | C23: 9055 | D23: ='INCOME STATEMENT'!D12*ASSUMPTIONS!D27/ASSUMPTIONS!D35 -> 10048.517 | E23: ='INCOME STATEMENT'!E12*ASSUMPTIONS!E27/ASSUMPTIONS!E35 -> 11153.854 | F23: ='INCOME STATEMENT'!F12*ASSUMPTIONS!F27/ASSUMPTIONS!F35 -> 12269.24 | G23: ='INCOME STATEMENT'!G12*ASSUMPTIONS!G27/ASSUMPTIONS!G35 -> 13373.471 | H23: ='INCOME STATEMENT'!H12*ASSUMPTIONS!H27/ASSUMPTIONS!H35 -> 14577.084
A24: Debt (Commercial Paper + Term Debt) | B24: 106629 | C24: 98657 | D24: ='SUPPORTING SCHEDULES'!D24 -> 89657 | E24: ='SUPPORTING SCHEDULES'!E24 -> 81657 | F24: ='SUPPORTING SCHEDULES'!F24 -> 74657 | G24: ='SUPPORTING SCHEDULES'!G24 -> 68657 | H24: ='SUPPORTING SCHEDULES'!H24 -> 63657
A25: Other Current Liabilities | B25: 78304 | C25: 66387 | D25: =C25 -> 66387 | E25: =D25 -> 66387 | F25: =E25 -> 66387 | G25: =F25 -> 66387 | H25: =G25 -> 66387
A26: Other Non-current Liabilities | B26: 45888 | C26: 41549 | D26: =C26 -> 41549 | E26: =D26 -> 41549 | F26: =E26 -> 41549 | G26: =F26 -> 41549 | H26: =G26 -> 41549
A27: Total Liabilities | B27: =SUM(B22:B26) -> 308030 | C27: =SUM(C22:C26) -> 285508 | D27: =SUM(D22:D26) -> 280900.65 | E27: =SUM(E22:E26) -> 276772.74 | F27: =SUM(F22:F26) -> 273365.71 | G27: =SUM(G22:G26) -> 271791.86 | H27: =SUM(H22:H26) -> 270625.41
A29: Shareholders' Equity
A30: Common Stock & Additional Paid-in Capital | B30: 83276 | C30: 93568 | D30: =C30+'CASH FLOW STATEMENT'!D9 -> 106721.51 | E30: =D30+'CASH FLOW STATEMENT'!E9 -> 120568.1 | F30: =E30+'CASH FLOW STATEMENT'!F9 -> 135153.75 | G30: =F30+'CASH FLOW STATEMENT'!G9 -> 150491.57 | H30: =G30+'CASH FLOW STATEMENT'!H9 -> 166629.97
A31: Retained Earnings / (Accumulated Deficit) | B31: -19154 | C31: -14264 | D31: =C31+'INCOME STATEMENT'!D32+ASSUMPTIONS!D33+ASSUMPTIONS!D34 -> -4387.01 | E31: =D31+'INCOME STATEMENT'!E32+ASSUMPTIONS!E33+ASSUMPTIONS!E34 -> 13934.96 | F31: =E31+'INCOME STATEMENT'!F32+ASSUMPTIONS!F33+ASSUMPTIONS!F34 -> 42880.426 | G31: =F31+'INCOME STATEMENT'!G32+ASSUMPTIONS!G33+ASSUMPTIONS!G34 -> 80130.245 | H31: =G31+'INCOME STATEMENT'!H32+ASSUMPTIONS!H33+ASSUMPTIONS!H34 -> 129035.54
A32: Accumulated Other Comprehensive Loss (AOCI) | B32: -7172 | C32: -5571 | D32: =C32 -> -5571 | E32: =D32 -> -5571 | F32: =E32 -> -5571 | G32: =F32 -> -5571 | H32: =G32 -> -5571
A33: Total Shareholders' Equity | B33: =SUM(B30:B32) -> 56950 | C33: =SUM(C30:C32) -> 73733 | D33: =SUM(D30:D32) -> 96763.498 | E33: =SUM(E30:E32) -> 128932.05 | F33: =SUM(F30:F32) -> 172463.18 | G33: =SUM(G30:G32) -> 225050.82 | H33: =SUM(H30:H32) -> 290094.51
A34: Total Liabilities & Shareholders' Equity | B34: =B27+B33 -> 364980 | C34: =C27+C33 -> 359241 | D34: =D27+D33 -> 377664.15 | E34: =E27+E33 -> 405704.79 | F34: =F27+F33 -> 445828.89 | G34: =G27+G33 -> 496842.68 | H34: =H27+H33 -> 560719.92
A36: Check | B36: =B19-B34 -> 0 | C36: =C19-C34 -> 0 | D36: =D19-D34 -> 0 | E36: =E19-E34 -> 0 | F36: =F19-F34 -> 0 | G36: =G19-G34 -> 0 | H36: =H19-H34 -> 0

Sheet CASH FLOW STATEMENT
B1: Historical Results | D1: Forecast Period
B2: 2024A | C2: 2025A | D2: 2026F | E2: 2027F | F2: 2028F | G2: 2029F | H2: 2030F
A4: Cash Flow Statement
A6: Operating Cash Flow
A7: Net Income | B7: ='INCOME STATEMENT'!B32 -> 93736 | C7: ='INCOME STATEMENT'!C32 -> 112010 | D7: ='INCOME STATEMENT'!D32 -> 121076.99 | E7: ='INCOME STATEMENT'!E32 -> 130321.97 | F7: ='INCOME STATEMENT'!F32 -> 141795.47 | G7: ='INCOME STATEMENT'!G32 -> 150999.82 | H7: ='INCOME STATEMENT'!H32 -> 163605.3
A8: Plus: Depreciation & Amortization | B8: 11445 | C8: 11698 | D8: ='SUPPORTING SCHEDULES'!D18 -> 11461.82 | E8: ='SUPPORTING SCHEDULES'!E18 -> 11930.601 | F8: ='SUPPORTING SCHEDULES'!F18 -> 12249.355 | G8: ='SUPPORTING SCHEDULES'!G18 -> 12980.75 | H8: ='SUPPORTING SCHEDULES'!H18 -> 13466.524
A9: Plus: Share-based Compensation | B9: 11688 | C9: 12863 | D9: ='INCOME STATEMENT'!D13*ASSUMPTIONS!D37 -> 13153.508 | E9: ='INCOME STATEMENT'!E13*ASSUMPTIONS!E37 -> 13846.587 | F9: ='INCOME STATEMENT'!F13*ASSUMPTIONS!F37 -> 14585.659 | G9: ='INCOME STATEMENT'!G13*ASSUMPTIONS!G37 -> 15337.82 | H9: ='INCOME STATEMENT'!H13*ASSUMPTIONS!H37 -> 16138.392
A10: Plus/(Less): Changes in Net Working Capital | B10: -170 | C10: =-'SUPPORTING SCHEDULES'!C13 -> -3440 | D10: =-'SUPPORTING SCHEDULES'!D13 -> 1128.47 | E10: =-'SUPPORTING SCHEDULES'!E13 -> -351.96673 | F10: =-'SUPPORTING SCHEDULES'!F13 -> -870.98568 | G10: =-'SUPPORTING SCHEDULES'!G13 -> -185.27097 | H10: =-'SUPPORTING SCHEDULES'!H13 -> -997.26631
A11: Other Non-cash Adjustments | B11: 0 | C11: 0 | D11: 0 | E11: 0 | F11: 0 | G11: 0 | H11: 0
A12: Cash from Operations | B12: =SUM(B7:B11) -> 116699 | C12: =SUM(C7:C11) -> 133131 | D12: =SUM(D7:D11) -> 146820.79 | E12: =SUM(E7:E11) -> 155747.19 | F12: =SUM(F7:F11) -> 167759.5 | G12: =SUM(G7:G11) -> 179133.12 | H12: =SUM(H7:H11) -> 192212.95
A14: Investing Cash Flow
A15: Capital Expenditures | B15: -9447 | C15: -12715 | D15: =ASSUMPTIONS!D30 -> -13500 | E15: =ASSUMPTIONS!E30 -> -14500 | F15: =ASSUMPTIONS!F30 -> -15500 | G15: =ASSUMPTIONS!G30 -> -16500 | H15: =ASSUMPTIONS!H30 -> -17500
A16: Cash from Investing | B16: =SUM(B15) -> -9447 | C16: =SUM(C15) -> -12715 | D16: =SUM(D15) -> -13500 | E16: =SUM(E15) -> -14500 | F16: =SUM(F15) -> -15500 | G16: =SUM(G15) -> -16500 | H16: =SUM(H15) -> -17500
A18: Financing Cash Flow
A19: Debt Issuance (Repayment), net | B19: =ASSUMPTIONS!B31+ASSUMPTIONS!B32 -> -5998 | C19: =ASSUMPTIONS!C31+ASSUMPTIONS!C32 -> -8483 | D19: =ASSUMPTIONS!D31+ASSUMPTIONS!D32 -> -9000 | E19: =ASSUMPTIONS!E31+ASSUMPTIONS!E32 -> -8000 | F19: =ASSUMPTIONS!F31+ASSUMPTIONS!F32 -> -7000 | G19: =ASSUMPTIONS!G31+ASSUMPTIONS!G32 -> -6000 | H19: =ASSUMPTIONS!H31+ASSUMPTIONS!H32 -> -5000
A20: Dividends Paid | B20: =ASSUMPTIONS!B33 -> -15234 | C20: =ASSUMPTIONS!C33 -> -15421 | D20: =ASSUMPTIONS!D33 -> -16200 | E20: =ASSUMPTIONS!E33 -> -17000 | F20: =ASSUMPTIONS!F33 -> -17850 | G20: =ASSUMPTIONS!G33 -> -18750 | H20: =ASSUMPTIONS!H33 -> -19700
A21: Share Repurchases | B21: =ASSUMPTIONS!B34 -> -94949 | C21: =ASSUMPTIONS!C34 -> -90711 | D21: =ASSUMPTIONS!D34 -> -95000 | E21: =ASSUMPTIONS!E34 -> -95000 | F21: =ASSUMPTIONS!F34 -> -95000 | G21: =ASSUMPTIONS!G34 -> -95000 | H21: =ASSUMPTIONS!H34 -> -95000
A22: Cash from Financing | B22: =SUM(B19:B21) -> -116181 | C22: =SUM(C19:C21) -> -114615 | D22: =SUM(D19:D21) -> -120200 | E22: =SUM(E19:E21) -> -120000 | F22: =SUM(F19:F21) -> -119850 | G22: =SUM(G19:G21) -> -119750 | H22: =SUM(H19:H21) -> -119700
A24: Net Increase (Decrease) in Cash | B24: =B12+B16+B22 -> -8929 | C24: =C12+C16+C22 -> 5801 | D24: =D12+D16+D22 -> 13120.788 | E24: =E12+E16+E22 -> 21247.191 | F24: =F12+F16+F22 -> 32409.495 | G24: =G12+G16+G22 -> 42883.118 | H24: =H12+H16+H22 -> 55012.949
A25: Opening Cash Balance | B25: 30737 | C25: =B26 -> 21808 | D25: ='BALANCE SHEET'!C7 -> 35934 | E25: =D26 -> 49054.788 | F25: =E26 -> 70301.979 | G25: =F26 -> 102711.47 | H25: =G26 -> 145594.59
A26: Closing Cash Balance | B26: =B24+B25 -> 21808 | C26: =C24+C25 -> 27609 | D26: =D24+D25 -> 49054.788 | E26: =E24+E25 -> 70301.979 | F26: =F24+F25 -> 102711.47 | G26: =G24+G25 -> 145594.59 | H26: =H24+H25 -> 200607.54

Sheet SUPPORTING SCHEDULES
B1: Historical Results | D1: Forecast Period
B2: 2024A | C2: 2025A | D2: 2026F | E2: 2027F | F2: 2028F | G2: 2029F | H2: 2030F
A4: Supporting Schedules
A6: Working Capital Schedule
A7: Accounts Receivable | B7: ='BALANCE SHEET'!B9 -> 33410 | C7: ='BALANCE SHEET'!C9 -> 39777 | D7: ='BALANCE SHEET'!D9 -> 39640.709 | E7: ='BALANCE SHEET'!E9 -> 41729.44 | F7: ='BALANCE SHEET'!F9 -> 43956.781 | G7: ='BALANCE SHEET'!G9 -> 46223.568 | H7: ='BALANCE SHEET'!H9 -> 48636.249
A8: Vendor Non-Trade Receivables | B8: ='BALANCE SHEET'!B10 -> 32833 | C8: ='BALANCE SHEET'!C10 -> 33180 | D8: ='BALANCE SHEET'!D10 -> 36037.008 | E8: ='BALANCE SHEET'!E10 -> 37935.855 | F8: ='BALANCE SHEET'!F10 -> 39960.71 | G8: ='BALANCE SHEET'!G10 -> 42021.425 | H8: ='BALANCE SHEET'!H10 -> 44214.772
A9: Inventory | B9: ='BALANCE SHEET'!B11 -> 7286 | C9: ='BALANCE SHEET'!C11 -> 5718 | D9: ='BALANCE SHEET'!D11 -> 6261.4645 | E9: ='BALANCE SHEET'!E11 -> 6497.9387 | F9: ='BALANCE SHEET'!F11 -> 6709.698 | G9: ='BALANCE SHEET'!G11 -> 6993.6232 | H9: ='BALANCE SHEET'!H11 -> 7218.4036
A10: Accounts Payable | B10: ='BALANCE SHEET'!B22 -> 68960 | C10: ='BALANCE SHEET'!C22 -> 69860 | D10: ='BALANCE SHEET'!D22 -> 73259.135 | E10: ='BALANCE SHEET'!E22 -> 76025.883 | F10: ='BALANCE SHEET'!F22 -> 78503.467 | G10: ='BALANCE SHEET'!G22 -> 81825.391 | H10: ='BALANCE SHEET'!H22 -> 84455.322
A11: Deferred Revenue | B11: ='BALANCE SHEET'!B23 -> 8249 | C11: ='BALANCE SHEET'!C23 -> 9055 | D11: ='BALANCE SHEET'!D23 -> 10048.517 | E11: ='BALANCE SHEET'!E23 -> 11153.854 | F11: ='BALANCE SHEET'!F23 -> 12269.24 | G11: ='BALANCE SHEET'!G23 -> 13373.471 | H11: ='BALANCE SHEET'!H23 -> 14577.084
A12: Net Working Capital (NWC) | B12: =SUM(B7:B9)-SUM(B10:B11) -> -3680 | C12: =SUM(C7:C9)-SUM(C10:C11) -> -240 | D12: =SUM(D7:D9)-SUM(D10:D11) -> -1368.47 | E12: =SUM(E7:E9)-SUM(E10:E11) -> -1016.5033 | F12: =SUM(F7:F9)-SUM(F10:F11) -> -145.5176 | G12: =SUM(G7:G9)-SUM(G10:G11) -> 39.753378 | H12: =SUM(H7:H9)-SUM(H10:H11) -> 1037.0197
A13: Change in NWC | C13: =C12-B12 -> 3440 | D13: =D12-C12 -> -1128.47 | E13: =E12-D12 -> 351.96673 | F13: =F12-E12 -> 870.98568 | G13: =G12-F12 -> 185.27097 | H13: =H12-G12 -> 997.26631
A15: Depreciation Schedule
A16: PP&E Opening | D16: =C19 -> 49834 | E16: =D19 -> 51872.18 | F16: =E19 -> 54441.579 | G16: =F19 -> 57692.223 | H16: =G19 -> 61211.473
A17: Plus: Capital Expenditures | D17: =-ASSUMPTIONS!D30 -> 13500 | E17: =-ASSUMPTIONS!E30 -> 14500 | F17: =-ASSUMPTIONS!F30 -> 15500 | G17: =-ASSUMPTIONS!G30 -> 16500 | H17: =-ASSUMPTIONS!H30 -> 17500
A18: Less: Depreciation & Amortization | D18: =D16*ASSUMPTIONS!D18 -> 11461.82 | E18: =E16*ASSUMPTIONS!E18 -> 11930.601 | F18: =F16*ASSUMPTIONS!F18 -> 12249.355 | G18: =G16*ASSUMPTIONS!G18 -> 12980.75 | H18: =H16*ASSUMPTIONS!H18 -> 13466.524
A19: PP&E Closing | B19: ='BALANCE SHEET'!B16 -> 45680 | C19: ='BALANCE SHEET'!C16 -> 49834 | D19: =D16+D17-D18 -> 51872.18 | E19: =E16+E17-E18 -> 54441.579 | F19: =F16+F17-F18 -> 57692.223 | G19: =G16+G17-G18 -> 61211.473 | H19: =H16+H17-H18 -> 65244.949
A21: Debt Schedule
A22: Debt Opening | D22: =C24 -> 98657 | E22: =D24 -> 89657 | F22: =E24 -> 81657 | G22: =F24 -> 74657 | H22: =G24 -> 68657
A23: Issuance (Repayment), net | D23: =ASSUMPTIONS!D31+ASSUMPTIONS!D32 -> -9000 | E23: =ASSUMPTIONS!E31+ASSUMPTIONS!E32 -> -8000 | F23: =ASSUMPTIONS!F31+ASSUMPTIONS!F32 -> -7000 | G23: =ASSUMPTIONS!G31+ASSUMPTIONS!G32 -> -6000 | H23: =ASSUMPTIONS!H31+ASSUMPTIONS!H32 -> -5000
A24: Debt Closing | B24: ='BALANCE SHEET'!B24 -> 106629 | C24: ='BALANCE SHEET'!C24 -> 98657 | D24: =D22+D23 -> 89657 | E24: =E22+E23 -> 81657 | F24: =F22+F23 -> 74657 | G24: =G22+G23 -> 68657 | H24: =H22+H23 -> 63657
